displayrws/__init__.py
displayrws/py.typed
displayrws-0.1.4.dist-info/LICENSE
displayrws-0.1.4.dist-info/METADATA
displayrws-0.1.4.dist-info/WHEEL
displayrws-0.1.4.dist-info/top_level.txt
displayrws-0.1.4.dist-info/RECORD
